{"茨城県": {"number_str": "約1200軒", "number": 1200, "timestamp": "2019-10-12T10:50:02.782646", "source": "http://teideninfo.tepco.co.jp/html/00000000000.html", "author": "出典:東京電力パワーグリッド Webサイト / 非公式API: https://ryo-a.github.io/jp-power-outage/", "cities": {"稲敷市": {"number_str": "約1000軒", "number": 1000, "areas": {"阿波": {"number_str": "100軒未満", "number": 100, "less_than": true}, "上馬渡": {"number_str": "100軒未満", "number": 100, "less_than": true}, "阿波崎": {"number_str": "100軒未満", "number": 100, "less_than": true}, "四箇": {"number_str": "約200軒", "number": 200}, "甘田": {"number_str": "約100軒", "number": 100}, "下馬渡": {"number_str": "100軒未満", "number": 100, "less_than": true}, "飯出": {"number_str": "約100軒", "number": 100}, "須賀津": {"number_str": "約100軒", "number": 100}, "伊佐部": {"number_str": "100軒未満", "number": 100, "less_than": true}, "西の洲": {"number_str": "100軒未満", "number": 100, "less_than": true}, "岡飯出": {"number_str": "100軒未満", "number": 100, "less_than": true}, "古渡": {"number_str": "100軒未満", "number": 100, "less_than": true}, "柏木": {"number_str": "100軒未満", "number": 100, "less_than": true}, "堀之内": {"number_str": "100軒未満", "number": 100, "less_than": true}, "柏木古渡": {"number_str": "100軒未満", "number": 100, "less_than": true}, "三次": {"number_str": "約100軒", "number": 100}, "釜井": {"number_str": "100軒未満", "number": 100, "less_than": true}, "南山来": {"number_str": "100軒未満", "number": 100, "less_than": true}}}, "笠間市": {"number_str": "100軒未満", "number": 100, "areas": {"押辺": {"number_str": "100軒未満", "number": 100, "less_than": true}}}, "水戸市": {"number_str": "約200軒", "number": 200, "areas": {"元吉田町": {"number_str": "約200軒", "number": 200}}}}}}