{"埼玉県": {"number_str": "約2100軒", "number": 2100, "timestamp": "2019-10-14T12:50:11.968247", "source": "http://teideninfo.tepco.co.jp/html/00000000000.html", "author": "出典:東京電力パワーグリッド Webサイト / 非公式API: https://ryo-a.github.io/jp-power-outage/", "cities": {"川島町": {"number_str": "100軒未満", "number": 100, "areas": {"大字長楽": {"number_str": "100軒未満", "number": 100, "less_than": true}, "大字吹塚": {"number_str": "100軒未満", "number": 100, "less_than": true}}}, "さいたま市西区": {"number_str": "約500軒", "number": 500, "areas": {"大字土屋": {"number_str": "100軒未満", "number": 100, "less_than": true}, "大字二ツ宮": {"number_str": "約400軒", "number": 400}, "大字西遊馬": {"number_str": "約100軒", "number": 100}}}, "東松山市": {"number_str": "約1500軒", "number": 1500, "areas": {"大字今泉": {"number_str": "100軒未満", "number": 100, "less_than": true}, "大字高坂": {"number_str": "約100軒", "number": 100}, "大字大黒部": {"number_str": "100軒未満", "number": 100, "less_than": true}, "大字早俣": {"number_str": "100軒未満", "number": 100, "less_than": true}, "大字毛塚": {"number_str": "約400軒", "number": 400}, "大字宮鼻": {"number_str": "約600軒", "number": 600}, "大字下押垂": {"number_str": "100軒未満", "number": 100, "less_than": true}, "元宿１丁目": {"number_str": "100軒未満", "number": 100, "less_than": true}, "大字正代": {"number_str": "約300軒", "number": 300}}}}}}