{"東京都": {"number_str": "約1000軒", "number": 1000, "timestamp": "2019-10-14T22:50:35.183354", "source": "http://teideninfo.tepco.co.jp/html/00000000000.html", "author": "出典:東京電力パワーグリッド Webサイト / 非公式API: https://ryo-a.github.io/jp-power-outage/", "cities": {"江東区": {"number_str": "約100軒", "number": 100, "areas": {"新木場１丁目": {"number_str": "約100軒", "number": 100}, "夢の島２丁目": {"number_str": "100軒未満", "number": 100, "less_than": true}, "新木場４丁目": {"number_str": "100軒未満", "number": 100, "less_than": true}, "夢の島３丁目": {"number_str": "100軒未満", "number": 100, "less_than": true}, "夢の島１丁目": {"number_str": "100軒未満", "number": 100, "less_than": true}}}, "世田谷区": {"number_str": "約900軒", "number": 900, "areas": {"上野毛２丁目": {"number_str": "約700軒", "number": 700}, "野毛３丁目": {"number_str": "約200軒", "number": 200}}}}}}